{
	"name": "greenpeace/planet4-test-rhea",
	"description": "Greenpeace P4 test-rhea",
	"license": "MIT",
	"require": {
		"greenpeace/planet4-master-theme": "7",
		"greenpeace/planet4-plugin-gutenberg-blocks": "7"
	},
	"repositories": [
		{
			"type": "package",
			"package": {
				"name": "greenpeace/planet4-plugin-gutenberg-blocks",
				"type": "wordpress-plugin",
				"autoload": null,
				"extra": null,
				"version": 7,
				"dist": {
					"type": "zip",
					"url": "https://storage.googleapis.com/planet4-packages/planet4-plugin-gutenberg-blocks/74003aa67c67bb88b077614c8e5011c88ad93af5.zip"
				}
			}
		},
		{
			"type": "package",
			"package": {
				"name": "greenpeace/planet4-master-theme",
				"type": "wordpress-theme",
				"autoload": {
					"psr-4": {
						"P4\\MasterTheme\\": "src/"
					}
				},
				"extra": {
					"installer-paths": {
						"vendor/plugins/{$name}/": [
							"type:wordpress-plugin"
						]
					}
				},
				"version": 7,
				"dist": {
					"type": "zip",
					"url": "https://storage.googleapis.com/planet4-packages/planet4-master-theme/933e03a4cb24091420fb6029ed60319929a89326.zip"
				}
			}
		}
	]
}
