{
	"name": "greenpeace/planet4-test-rhea",
	"description": "Greenpeace P4 test-rhea",
	"license": "MIT",
	"require": {
		"greenpeace/planet4-master-theme": "7",
		"greenpeace/planet4-plugin-gutenberg-blocks": "dev-main"
	},
	"repositories": [
		{
			"type": "package",
			"package": {
				"name": "greenpeace/planet4-master-theme",
				"type": "wordpress-theme",
				"autoload": {
					"psr-4": {
						"P4\\MasterTheme\\": "src/"
					}
				},
				"extra": {
					"installer-paths": {
						"vendor/plugins/{$name}/": [
							"type:wordpress-plugin"
						]
					}
				},
				"version": 7,
				"dist": {
					"type": "zip",
					"url": "https://storage.googleapis.com/planet4-packages/planet4-master-theme/91e64aa0d3eb36c25233dc8a857b30a5c02f35d6.zip"
				}
			}
		}
	]
}
